gitbridge/AGENTS.md
gitbridge/__init__.py
gitbridge/api_client.py
gitbridge/api_sync.py
gitbridge/browser_sync.py
gitbridge/cert_support.py
gitbridge/cli.py
gitbridge/config.py
gitbridge/exceptions.py
gitbridge/file_synchronizer.py
gitbridge/interfaces.py
gitbridge/pac_support.py
gitbridge/progress_tracker.py
gitbridge/repository_manager.py
gitbridge/session_factory.py
gitbridge/utils.py
gitbridge-1.0.4.dist-info/WHEEL
gitbridge-1.0.4.dist-info/entry_points.txt
gitbridge-1.0.4.dist-info/METADATA
gitbridge-1.0.4.dist-info/RECORD
