Metadata-Version: 2.3
Name: gitbridge
Version: 1.0.4
Summary: Synchronize GitHub repositories when git access is blocked
Author: Nevedomski Sergei
Author-email: Nevedomski Sergei <info@nevedomski.us>
License: MIT
Classifier: Programming Language :: Python :: 3
Classifier: Programming Language :: Python :: 3.10
Classifier: Programming Language :: Python :: 3.11
Classifier: Programming Language :: Python :: 3.12
Classifier: License :: OSI Approved :: MIT License
Classifier: Operating System :: OS Independent
Requires-Dist: requests>=2.31.0
Requires-Dist: pyyaml>=6.0
Requires-Dist: click>=8.1.0
Requires-Dist: python-dotenv>=1.0.0
Requires-Dist: tqdm>=4.66.0
Requires-Dist: certifi>=2023.0.0
Requires-Dist: pypac>=0.16.0 ; sys_platform == 'win32'
Requires-Dist: wincertstore>=0.2.0 ; sys_platform == 'win32'
Requires-Dist: pywin32>=300 ; sys_platform == 'win32'
Requires-Dist: pytest>=7.4.0 ; extra == 'all'
Requires-Dist: pytest-cov>=4.1.0 ; extra == 'all'
Requires-Dist: ruff>=0.1.0 ; extra == 'all'
Requires-Dist: mypy>=1.5.0 ; extra == 'all'
Requires-Dist: types-requests>=2.31.0 ; extra == 'all'
Requires-Dist: types-pyyaml>=6.0 ; extra == 'all'
Requires-Dist: types-tqdm>=4.66.0 ; extra == 'all'
Requires-Dist: mkdocs>=1.6.0 ; extra == 'all'
Requires-Dist: mkdocs-material>=9.6.16 ; extra == 'all'
Requires-Dist: mkdocs-material-extensions>=1.3.1 ; extra == 'all'
Requires-Dist: pymdown-extensions>=10.8 ; extra == 'all'
Requires-Dist: mkdocs-git-revision-date-localized-plugin>=1.4.7 ; extra == 'all'
Requires-Dist: mkdocs-minify-plugin>=0.8.0 ; extra == 'all'
Requires-Dist: mkdocstrings[python]>=0.30.0 ; extra == 'all'
Requires-Dist: pillow>=10.4.0 ; extra == 'all'
Requires-Dist: cairosvg>=2.7.1 ; extra == 'all'
Requires-Dist: playwright>=1.40.0 ; extra == 'all'
Requires-Dist: playwright>=1.40.0 ; extra == 'browser'
Requires-Dist: pytest>=7.4.0 ; extra == 'dev'
Requires-Dist: pytest-cov>=4.1.0 ; extra == 'dev'
Requires-Dist: ruff>=0.1.0 ; extra == 'dev'
Requires-Dist: mypy>=1.5.0 ; extra == 'dev'
Requires-Dist: types-requests>=2.31.0 ; extra == 'dev'
Requires-Dist: types-pyyaml>=6.0 ; extra == 'dev'
Requires-Dist: types-tqdm>=4.66.0 ; extra == 'dev'
Requires-Dist: mkdocs>=1.6.0 ; extra == 'docs'
Requires-Dist: mkdocs-material>=9.6.16 ; extra == 'docs'
Requires-Dist: mkdocs-material-extensions>=1.3.1 ; extra == 'docs'
Requires-Dist: pymdown-extensions>=10.8 ; extra == 'docs'
Requires-Dist: mkdocs-git-revision-date-localized-plugin>=1.4.7 ; extra == 'docs'
Requires-Dist: mkdocs-minify-plugin>=0.8.0 ; extra == 'docs'
Requires-Dist: mkdocstrings[python]>=0.30.0 ; extra == 'docs'
Requires-Dist: pillow>=10.4.0 ; extra == 'docs'
Requires-Dist: cairosvg>=2.7.1 ; extra == 'docs'
Requires-Python: >=3.10
Project-URL: Changelog, https://nevedomski.github.io/gitbridge/changelog.html
Project-URL: Documentation, https://nevedomski.github.io/gitbridge/
Project-URL: Homepage, https://nevedomski.github.io/gitbridge/
Project-URL: Issues, https://github.com/nevedomski/gitbridge/issues
Project-URL: Repository, https://github.com/nevedomski/gitbridge
Provides-Extra: all
Provides-Extra: browser
Provides-Extra: dev
Provides-Extra: docs
